pynanopore/__init__.py
pynanopore/app.py
pynanopore/dwelltime.py
pynanopore/event_detection.py
pynanopore/powerspectrum.py
pynanopore-1.1.1.dist-info/METADATA
pynanopore-1.1.1.dist-info/WHEEL
pynanopore-1.1.1.dist-info/top_level.txt
pynanopore-1.1.1.dist-info/RECORD
