Metadata-Version: 2.1
Name: pynanopore
Version: 1.1.1
Home-page: https://github.com/jaybfn/Single-Molecule-Electrophysiology-Data-Analysis
Author: Jayesh Arun Bafna
Author-email: jayesh.bfn@gmail.com
License: MIT
Requires-Python: >=3.11
Requires-Dist: pandas >=2.1.0
Requires-Dist: streamlit >=1.26.0
Requires-Dist: plotly >=5.16.1
Requires-Dist: plotly-express >=0.4.1
Requires-Dist: pyabf >=2.3.8
Requires-Dist: scipy >=1.11.3
Requires-Dist: wheel
Requires-Dist: pytest
Provides-Extra: dev
Requires-Dist: pytest ; extra == 'dev'
Requires-Dist: twine ; extra == 'dev'
